nqrduck_spectrometer_limenqr/__init__.py
nqrduck_spectrometer_limenqr/controller.py
nqrduck_spectrometer_limenqr/limenqr.py
nqrduck_spectrometer_limenqr/model.py
nqrduck_spectrometer_limenqr/view.py
nqrduck_spectrometer_limenqr/resources/limenqr.ini
nqrduck_spectrometer_limenqr/resources/limenqr_widget.ui
nqrduck_spectrometer_limenqr-0.0.9.dist-info/METADATA
nqrduck_spectrometer_limenqr-0.0.9.dist-info/WHEEL
nqrduck_spectrometer_limenqr-0.0.9.dist-info/entry_points.txt
nqrduck_spectrometer_limenqr-0.0.9.dist-info/licenses/LICENSE
nqrduck_spectrometer_limenqr-0.0.9.dist-info/RECORD
