Metadata-Version: 2.4
Name: nqrduck-spectrometer-limenqr
Version: 0.0.9
Summary: A submodule for the nqrduck-spectrometer module which implements the functionality for the LimeNQR spectrometer.
Project-URL: Homepage, https://nqrduck.cool
Project-URL: Bug Tracker, https://git.private.coffee/nqrduck/nqrduck-spectrometer-limenqr/issues
Project-URL: Source Code, https://git.private.coffee/nqrduck/nqrduck-spectrometer-limenqr
Author-email: jupfi <support@nqrduck.cool>
License: MIT License
License-File: LICENSE
Classifier: License :: OSI Approved :: MIT License
Classifier: Operating System :: POSIX :: Linux
Classifier: Programming Language :: Python :: 3
Requires-Python: >=3.10
Requires-Dist: h5py
Requires-Dist: limedriver
Requires-Dist: nqrduck-spectrometer
Requires-Dist: pyqt6
Requires-Dist: pyserial
Requires-Dist: quackseq-limenqr
